discordailib/__init__.py
discordailib/client.py
discordailib/models.py
discordailib/utils.py
discordai_lib-1.2.0.dist-info/LICENSE
discordai_lib-1.2.0.dist-info/METADATA
discordai_lib-1.2.0.dist-info/WHEEL
discordai_lib-1.2.0.dist-info/top_level.txt
discordai_lib-1.2.0.dist-info/RECORD
