Metadata-Version: 2.1
Name: discordai-lib
Version: 1.2.0
Summary: Easy AI integration for Discord bots using Pollination.ai
Home-page: https://github.com/VyeronServices/discordai-lib
Author: VyeronServices
Author-email: vyeronservices.official@gmail.com
Project-URL: Bug Reports, https://github.com/VyeronServices/discordai-lib/issues
Project-URL: Source, https://github.com/VyeronServices/discordai-lib
Project-URL: Documentation, https://github.com/VyeronServices/discordai-lib#readme
Project-URL: Discord Support, https://discord.gg/zsBNWvDu96
Keywords: discord,bot,ai,pollination,deepseek,grok,openai,chatbot,image generation
Classifier: Development Status :: 5 - Production/Stable
Classifier: Intended Audience :: Developers
Classifier: Topic :: Software Development :: Libraries :: Python Modules
Classifier: Topic :: Communications :: Chat
Classifier: Topic :: Internet :: WWW/HTTP :: Dynamic Content
Classifier: License :: OSI Approved :: MIT License
Classifier: Programming Language :: Python :: 3
Classifier: Programming Language :: Python :: 3.8
Classifier: Programming Language :: Python :: 3.9
Classifier: Programming Language :: Python :: 3.10
Classifier: Programming Language :: Python :: 3.11
Classifier: Programming Language :: Python :: 3.12
Requires-Python: >=3.8
License-File: LICENSE
Requires-Dist: aiohttp>=3.8.0
Requires-Dist: pytest
Requires-Dist: pytest-asyncio
Requires-Dist: twine
Requires-Dist: discord-py
Requires-Dist: discord.py>=2.3.0; extra == "discord"
Provides-Extra: discord
